{
  "Applications": {
    "{{$1}}-public-web-vue-open-source": {
      "Details": {
        "Description": "A basic starting point for sites built with Vue.",
        "Name": "Vue Quickstart Project - Open Source"
      },
      "LookupConfig": {
        "PathRegex": "/.*"
      },
      "Package": {
        "Details": {
          "Package": "@fathym-it/public-web-vue",
          "Version": "latest"
        },
        "Type": "NPMLowCodeUnit"
      },
      "Processor": {
        "Details": {
          "BaseHref": "/",
          "DefaultFile": "index.html"
        },
        "Type": "DFSProcessor"
      }
    }
  },
  "Projects": {
    "{{PROJECT_LOOKUP}}": {
      "ApplicationLookups": [
        "{{$1}}-public-web-vue-open-source"
      ]
    }
  }
}
